[
      {
            "tweet": "Em pensar q vou ter q acordar td semana as 7 me bate a maior tristeza",
            "sentiment": "tristeza"
      },
      {
            "tweet": "@camelaguru Aí, tristeza sabe vida  Mas o idiota aq se submete a essas coisas, parece q só assim eu fico afim d algm",
            "sentiment": "tristeza"
      },
      {
            "tweet": "@Gihamaral4 tristeza e decepção",
            "sentiment": "tristeza"
      },
      {
            "tweet": "Um certo alívio misturado com tristeza.",
            "sentiment": "tristeza"
      },
      {
            "tweet": "tem gente que ainda não ta me reconhecendoKKKK que tristeza",
            "sentiment": "tristeza"
      },
      {
            "tweet": "Aí que tristeza mané pprt, que isso 😔",
            "sentiment": "tristeza"
      },
      {
            "tweet": "sofrimento, tristeza e saudade noites de domingo",
            "sentiment": "tristeza"
      },
      {
            "tweet": "tristeza mórbida",
            "sentiment": "tristeza"
      },
      {
            "tweet": "Em pleno domingo à noite, infelizmente, somos obrigados a consumir mil vezes a imagem do presidente com a camisa da Havan, apontando para o logo do SBT, durante o jogo da seleção brasileira. Que tristeza. Bolsonaro não precisa pagar para ser divulgado.",
            "sentiment": "tristeza"
      },
      {
            "tweet": "urgente to me afogando em tristeza",
            "sentiment": "tristeza"
      },
      {
            "tweet": "@369HORAN sim, é uma tristeza isso viu",
            "sentiment": "tristeza"
      },
      {
            "tweet": "eu juro isso ia curar a tristeza que to sentindo",
            "sentiment": "tristeza"
      },
      {
            "tweet": "Enfim tristeza",
            "sentiment": "tristeza"
      },
      {
            "tweet": "@namoradodamitty nossa pq vc me deixa curiosa e dps fala q nn e nada nossa pq vv me odeia meus olhos brilharam pensando que nova informacao entraria nommeu cerebro que tristeza",
            "sentiment": "tristeza"
      },
      {
            "tweet": "tanta tristeza que nem cabe no peito!!! #decepcao#",
            "sentiment": "tristeza"
      },
      {
            "tweet": "meu deus que tristeza",
            "sentiment": "tristeza"
      },
      {
            "tweet": "Celebrar mais um ano  da vida de alguém que a gente ama, em meio a tanta tristeza, dor e perda, é emocionante! Muita gratidão por mais um dia 12 com a pessoa mais importante da minha vida aqui, espero que isso se repita por anos e mais anos",
            "sentiment": "tristeza"
      },
      {
            "tweet": "queria uma barca de sushi pra esquecer a tristeza",
            "sentiment": "tristeza"
      },
      {
            "tweet": "@baccarin_manu da até uma tristeza bacca",
            "sentiment": "tristeza"
      },
      {
            "tweet": "Quase sempre a gente confunde cansaço com tristeza.",
            "sentiment": "tristeza"
      },
      {
            "tweet": "@whodigoo tristeza profunda",
            "sentiment": "tristeza"
      },
      {
            "tweet": "Desde ontem eh estou fingindo que eu estou bem, para não dar explicações da minha tristeza 🥺😭",
            "sentiment": "tristeza"
      },
      {
            "tweet": "acordei que tristeza",
            "sentiment": "tristeza"
      },
      {
            "tweet": "chego em casa bate uma tristeza que só por Deus",
            "sentiment": "tristeza"
      },
      {
            "tweet": "@zlhnl_walls eu sou assim  q tristeza amg",
            "sentiment": "tristeza"
      },
      {
            "tweet": "@mariacpenasso_ sai ate a tristeza",
            "sentiment": "tristeza"
      },
      {
            "tweet": "@fairythay_ po mano perdoa  mas po acontecer isso logo no dia após o dia 12... Presente de grego",
            "sentiment": "tristeza"
      },
      {
            "tweet": "Lembrando em 2015 quando tive meu primeiro contato com o kpop e não era de fandom nenhum, escutava de tudo, eu vi a terceira geração se estabelecer, crescer e tô vendo ela acabar, que tristeza bicho, chorei tanto disband da segunda geração no off",
            "sentiment": "tristeza"
      },
      {
            "tweet": "A vida é muito irônica... Precisamos da tristeza para conhecermos a felicidade, do barulho para apreciarmos o silêncio e da ausência para valorizarmos a presença.",
            "sentiment": "tristeza"
      },
      {
            "tweet": "é um misto de tristeza e crise existêncial, ó delícia...",
            "sentiment": "tristeza"
      },
      {
            "tweet": "O tristeza",
            "sentiment": "tristeza"
      },
      {
            "tweet": "nunca mais. serio, nunca mais eu quero fazer amizade com pessoas que moram longe pra caralho. se eu pudesse eu me afastaria de todos só pra evitar a dor e tristeza que sinto por não poder abraçar todos e cuidar de pertinho, mas isso iria doer mais ainda. cara, que saco.",
            "sentiment": "tristeza"
      },
      {
            "tweet": "VOU TER QUE PARAR PRA JANTAR que  tristeza",
            "sentiment": "tristeza"
      },
      {
            "tweet": "@beaushineart Só tenho dela, uma tristeza",
            "sentiment": "tristeza"
      },
      {
            "tweet": "Tristeza não tem fim, mas felicidade sim.",
            "sentiment": "tristeza"
      },
      {
            "tweet": "terminei que tristeza eu amo vcs meus cavaleiros eu amo amo vcs",
            "sentiment": "tristeza"
      },
      {
            "tweet": "@woIfhard90s AMG Q TRISTEZA",
            "sentiment": "tristeza"
      },
      {
            "tweet": "meu deus que ódio eu amo ele, ele jogou nossa história em um poço sem fundo💔💔💔💔💔💔NZBAKAHAKAK q tristeza",
            "sentiment": "tristeza"
      },
      {
            "tweet": "@babi_aquinooo Eu não consigo não me culpar, as vezes parte de alguma tristeza dela foi minha culpa, eu fui uma idiota cara",
            "sentiment": "tristeza"
      },
      {
            "tweet": "Só de pensar que amanhã tenho que estar la de novo ja me bate uma tristeza",
            "sentiment": "tristeza"
      },
      {
            "tweet": "eu nem ia beber mais só q aí colocaram flavio jose boy um forrozinho raiz pqp chega deu uma tristeza",
            "sentiment": "tristeza"
      },
      {
            "tweet": "@iFEARLES91 tristeza? no es feliz",
            "sentiment": "tristeza"
      },
      {
            "tweet": "@KoepselYasmin @SCInternacional que tristeza",
            "sentiment": "tristeza"
      },
      {
            "tweet": "Toda vez q aparece pra mim o vídeo do gol do edenilson sendo anulado tenho vários tipos de tristeza",
            "sentiment": "tristeza"
      },
      {
            "tweet": "@fdalvinegro david braz e ganso titulares meu deus q tristeza",
            "sentiment": "tristeza"
      },
      {
            "tweet": "concurso público de pro player de valorant",
            "sentiment": "tristeza"
      },
      {
            "tweet": "@Krastyel_ Tomar um tiro",
            "sentiment": "tristeza"
      },
      {
            "tweet": "@brwnitzzz Tristeza nao tem fim",
            "sentiment": "tristeza"
      },
      {
            "tweet": "@Imjaguarj @Iuvsquin que tristeza",
            "sentiment": "tristeza"
      },
      {
            "tweet": "@N3G4TIV3S4TURN0 oOOOO tao lindinhos nhmmm🤧💞💞💞💞",
            "sentiment": "tristeza"
      },
      {
            "tweet": "a tristeza de chegar o domingo a noite e lembrar que tem que trabalhar no dia seguinte",
            "sentiment": "tristeza"
      },
      {
            "tweet": "@lovesickfornini que tristeza😭",
            "sentiment": "tristeza"
      },
      {
            "tweet": "eu tava tão bem esse fds mas foi so chegar em casa q a tristeza voltou",
            "sentiment": "tristeza"
      },
      {
            "tweet": "@carlaprvieira @_caaddss eu e a caaddss já tivemos nossas indiferenças mas eu sei que hoje a comunidade perdeu alguém sensacional  meus sentimentos a família",
            "sentiment": "tristeza"
      },
      {
            "tweet": "@tanjirofav Que tristeza",
            "sentiment": "tristeza"
      },
      {
            "tweet": "@jonis__ é uma tristeza ver ele jogando",
            "sentiment": "tristeza"
      },
      {
            "tweet": "@jamolestina Que tristeza :(",
            "sentiment": "tristeza"
      },
      {
            "tweet": "@negrendalf O mais impressionante foi ele ter arrancado essa merda",
            "sentiment": "tristeza"
      },
      {
            "tweet": "Foi minha companhia nos momentos de solidão e de tristeza (eu nunca chorei sozinha!)  Quando batem na minha cara, quem dá a outra face é Exu!  Saúdo a Energia que transita em todos os espaços!  Passos firmes Cabeça erguida!  Sigo. Segui. Seguirei até o fim!",
            "sentiment": "tristeza"
      },
      {
            "tweet": "@b4rneyJ @teamoneesports Tristeza por vc irmão ou por nós eu diria eu torço pro Coritiba e vc pra team one apenas tristeza.",
            "sentiment": "tristeza"
      },
      {
            "tweet": "@ysaintlouie to com fome, q tristeza",
            "sentiment": "tristeza"
      },
      {
            "tweet": "que tristeza meu fluminense",
            "sentiment": "tristeza"
      },
      {
            "tweet": "a tristeza q eu to por nunca ter chance cm o bryce nem cm o vinnie",
            "sentiment": "tristeza"
      },
      {
            "tweet": "@alvaro_goulart vc curou minha tristeza amigo obrigado",
            "sentiment": "tristeza"
      },
      {
            "tweet": "@rikacult @jiwoogogh @kaeyamandrake sim ke tristeza eu tinha mo nojo de homem, qnd eu via bis mostrando atracao genuina por homens eu achava esquisito pq n era a msm coisa q eu, ent eu pensava oq tinha de errado comigo",
            "sentiment": "tristeza"
      },
      {
            "tweet": "@saturxies nada que tristeza",
            "sentiment": "tristeza"
      },
      {
            "tweet": "Nossa cara que tristeza mano",
            "sentiment": "tristeza"
      },
      {
            "tweet": "meu deus q tristeza a utica.",
            "sentiment": "tristeza"
      },
      {
            "tweet": "@suzana_allen @SimoneRosado Caramba. Que tristeza.....",
            "sentiment": "tristeza"
      },
      {
            "tweet": "@naivergf ME DA TRISTEZA",
            "sentiment": "tristeza"
      },
      {
            "tweet": "@Im_One_Star eu encontro quem gosta de mais alta ou mais baixa ainda 🤡🤡🤡🤡🤡🤡🤡✌ tristeza profunda",
            "sentiment": "tristeza"
      },
      {
            "tweet": "que tristeza levoki não sei interagir mais",
            "sentiment": "tristeza"
      },
      {
            "tweet": "minha correntinha estourou meu deus que tristeza depois de anos usando sem tirar pra nada tô de luto",
            "sentiment": "tristeza"
      },
      {
            "tweet": "essa semana não teve 1 dia que eu acordei depois de meio dia e pouca, que tristeza",
            "sentiment": "tristeza"
      },
      {
            "tweet": "@siImarilIion que tristeza",
            "sentiment": "tristeza"
      },
      {
            "tweet": "a unica tristeza do frio, é que da vontade de ficar juntinho de alguém.",
            "sentiment": "tristeza"
      },
      {
            "tweet": "Essa minha tristeza só cabe em mim, eu já tentei explicar, já desenhei, escrevi, cantei! Mas com o tempo eu fui descobrindo que essa é uma imensidão que eu preciso agarrar com os braços e ela me engolirá.",
            "sentiment": "tristeza"
      },
      {
            "tweet": "as vezes eu lembro que fui trocada por uma **** que além de **** eh ***** de ***** bate uma tristeza sio",
            "sentiment": "tristeza"
      },
      {
            "tweet": "Que tristeza",
            "sentiment": "tristeza"
      },
      {
            "tweet": "@flvmntr Tia lenice perfeita",
            "sentiment": "tristeza"
      },
      {
            "tweet": "@potterazkbn gross é meu tudo, ouve dnv amg   e crazy so tem uns 30 segundos de qualquer jeito, uma tristeza",
            "sentiment": "tristeza"
      },
      {
            "tweet": "É bom demais dar concelho pra amigo mais novo",
            "sentiment": "tristeza"
      },
      {
            "tweet": "Que tristeza esse jogo do vitória",
            "sentiment": "tristeza"
      },
      {
            "tweet": "Que tristeza",
            "sentiment": "tristeza"
      },
      {
            "tweet": "Meu irmão colocou um filme na sala e só pela música da abertura identifiquei que era um do adam sandler e qual é especificamente... que tristeza",
            "sentiment": "tristeza"
      },
      {
            "tweet": "@pattzcoven então esse velho pensa q tristeza eh brincadeira",
            "sentiment": "tristeza"
      },
      {
            "tweet": "minha tristeza passa quando entro no tiktok e vejo mulheres rebolando",
            "sentiment": "tristeza"
      },
      {
            "tweet": "do nada a tristeza bateu",
            "sentiment": "tristeza"
      },
      {
            "tweet": "Que tristeza tudo isso 😭",
            "sentiment": "tristeza"
      },
      {
            "tweet": "@miyasarcasm Madu mata o fandom de tristeza: entenda o caso; QUE EDIT LINDA",
            "sentiment": "tristeza"
      },
      {
            "tweet": "já pararam p pensar oq seria de nós sem os melhores amigos do insta? tristeza pura pq eu amo postar minhas coisa inútil lá",
            "sentiment": "tristeza"
      },
      {
            "tweet": "nunca passo frio pois sempre estou coberta de tristeza",
            "sentiment": "tristeza"
      },
      {
            "tweet": "@ourminchan imaginei lek q tristeza",
            "sentiment": "tristeza"
      },
      {
            "tweet": "Finalizando o episódio do Leandro Bossi 😭😭🤧 bah ver visualmente é outra coisa né, bah tristeza 😭😭",
            "sentiment": "tristeza"
      },
      {
            "tweet": "ou seja depressao pqp é so tristeza esse algoritmo quer ver a gente triste",
            "sentiment": "tristeza"
      },
      {
            "tweet": "@clareouodia que tristeza",
            "sentiment": "tristeza"
      },
      {
            "tweet": "minha fav me deu unf que tristeza sério",
            "sentiment": "tristeza"
      },
      {
            "tweet": "@folkirwin @zhslot ki tristeza",
            "sentiment": "tristeza"
      },
      {
            "tweet": "@kmendoncafilho Sim, infelizmente tenho um irmão bozominiom, uma tristeza",
            "sentiment": "tristeza"
      },
      {
            "tweet": "perdi a briga na call q tristeza!!!",
            "sentiment": "tristeza"
      },
      {
            "tweet": "tristeza",
            "sentiment": "tristeza"
      },
      {
            "tweet": "@VlBEZWALLS Tristeza",
            "sentiment": "tristeza"
      },
      {
            "tweet": "@MoaresMargos meu deus que tristeza pra que tu mandou o link?",
            "sentiment": "tristeza"
      },
      {
            "tweet": "Tua tristeza e seu sofrimento de hj, lá na frente vai se transformar em alegria e vitória",
            "sentiment": "tristeza"
      },
      {
            "tweet": "Que tristeza",
            "sentiment": "tristeza"
      },
      {
            "tweet": "aquela tristeza básica dps de passar dois dias agarrada na sua namorada e ter que voltar pra casa 🥲 toda semana um sofrimento carai carai",
            "sentiment": "tristeza"
      },
      {
            "tweet": "@IEROC0RPSE exatamente KKKKKKKKKKK",
            "sentiment": "tristeza"
      },
      {
            "tweet": "tirando a foto do perfil por motivos de \\",
            "sentiment": "tristeza"
      },
      {
            "tweet": "fortaleza faça um gol eu tô mt triste só vc pra curar mh tristeza",
            "sentiment": "tristeza"
      },
      {
            "tweet": "@crowleyisonfire eu amo arctic monkeys mas AM (o album q tem do i wanna know) é mt ruim po 👎🤢 e o the ngbh concordo KKKKKKKKK",
            "sentiment": "tristeza"
      },
      {
            "tweet": "o t de vcs agora é de tesão,tédio ou tristeza?",
            "sentiment": "tristeza"
      },
      {
            "tweet": "ai q tristeza n vo ver a chata da evelyn a semana toda",
            "sentiment": "tristeza"
      },
      {
            "tweet": "da vontade d chroar d tristeza pois nunca vo namorar o jungkook gente eh serio eu to mt mal",
            "sentiment": "tristeza"
      },
      {
            "tweet": "Minha psicóloga quer que anote tudo com como e eu anoto e quero chorar de tristeza",
            "sentiment": "tristeza"
      },
      {
            "tweet": "Tristeza",
            "sentiment": "tristeza"
      },
      {
            "tweet": "@iKissEris Simm amg, esse o demônio só aparecia quando a mulher fazia os treco lá. Uma tristeza",
            "sentiment": "tristeza"
      },
      {
            "tweet": "@DheaORetorno @Antonio75084719 @fabyccouto Caramba. Ela estava melhorando da efermidade....Que tristeza....",
            "sentiment": "tristeza"
      },
      {
            "tweet": "que tristeza",
            "sentiment": "tristeza"
      },
      {
            "tweet": "lidando com a tristeza de um jeito saudável, vendo run bts e star wars. 😍",
            "sentiment": "tristeza"
      },
      {
            "tweet": "@viniciuusalves_ o q zikou foi esse plano de fundo, apenas tristeza e sofrimento",
            "sentiment": "tristeza"
      },
      {
            "tweet": "Esse fds foi uma mistura de muita alegria com muita tristeza tbm… eu tenho uns amigos perfeitos demais… não sei se o q eu faria sem eles",
            "sentiment": "tristeza"
      },
      {
            "tweet": "Tristeza",
            "sentiment": "tristeza"
      },
      {
            "tweet": "Tristeza do caralho.... Tá foda",
            "sentiment": "tristeza"
      },
      {
            "tweet": "@LoudBiia1 @loud_victor que tristeza amg 🥺😭🥺😭🥺",
            "sentiment": "tristeza"
      },
      {
            "tweet": "todo mundo enjoa de falar comigo, que tristeza",
            "sentiment": "tristeza"
      },
      {
            "tweet": "Domingo à noite a tristeza é grande demais, eu não quero trabalhar amanhã",
            "sentiment": "tristeza"
      },
      {
            "tweet": "Que tristeza cara, eu nunca vi coisa igual com um time",
            "sentiment": "tristeza"
      },
      {
            "tweet": "fiquei tristinha do nada, uma vontade de chorar ahha pelo menos meu pai do nada resolveu mandar dinheiro pra comprar pizza  afogar a tristeza aleatória em pizza",
            "sentiment": "tristeza"
      },
      {
            "tweet": "@juhantoni Queria tá ficando chapada  A única coisa q to sentindo é desgosto líquido",
            "sentiment": "tristeza"
      },
      {
            "tweet": "@dpsk_ Amigaaaaaa eu to rindo aqui  Uns eu bloqueei pq eram baixo nível, mas to até me distraindo da tristeza que eu tava",
            "sentiment": "tristeza"
      },
      {
            "tweet": "tristeza",
            "sentiment": "tristeza"
      },
      {
            "tweet": "Aquela tristeza Qnd ele volta pra casa 🥺",
            "sentiment": "tristeza"
      }
]